argparsing.py
main.py
zyra.py
cmds/__init__.py
cmds/add.py
cmds/checkout.py
cmds/commands.py
cmds/commit.py
cmds/commits.py
cmds/log.py
cmds/rm.py
cmds/status.py
cmds/tag.py
common/__init__.py
common/objects.py
common/repo.py
common/blob/__init__.py
common/blob/blob_obj.py
common/commit/__init__.py
common/commit/commit_helper.py
common/commit/commit_obj.py
common/tag/__init__.py
common/tag/tag_obj.py
common/tree/__init__.py
common/tree/tree_helper.py
common/tree/tree_obj.py
helpers/__init__.py
helpers/objects/__init__.py
helpers/objects/helpers.py
helpers/refs/__init__.py
helpers/refs/helpers.py
helpers/repo/__init__.py
helpers/repo/helpers.py
stage/__init__.py
stage/indexfile.py
stage/readwrite.py
zyra_tool-1.0.11.dist-info/METADATA
zyra_tool-1.0.11.dist-info/WHEEL
zyra_tool-1.0.11.dist-info/entry_points.txt
zyra_tool-1.0.11.dist-info/top_level.txt
zyra_tool-1.0.11.dist-info/RECORD
