Metadata-Version: 2.1
Name: zyra-tool
Version: 1.0.11
Summary: zyra: A version control system that is built from scratch in python
Home-page: https://github.com/karthik11135/zyra
Author: Karthik Rishinarada
Author-email: karthikdmy11135@gmail.com
License: UNKNOWN
Platform: UNKNOWN
Requires-Python: >=3.10
Requires-Dist: termcolor (>=2.2.0)
